NERDA/__init__.py
NERDA/datasets.py
NERDA/models.py
NERDA/networks.py
NERDA/performance.py
NERDA/precooked.py
NERDA/predictions.py
NERDA/preprocessing.py
NERDA/training.py
NERDA/utils.py
NERDA-1.0.0.dist-info/LICENSE
NERDA-1.0.0.dist-info/METADATA
NERDA-1.0.0.dist-info/WHEEL
NERDA-1.0.0.dist-info/top_level.txt
NERDA-1.0.0.dist-info/RECORD
