Metadata-Version: 2.1
Name: NERDA
Version: 1.0.0
Summary: A Framework for Finetuning Transformers for Named-Entity Recognition
Home-page: https://github.com/ebanalyse/NERDA
Author: Lars Kjeldgaard, Lukas Christian Nielsen
Author-email: lars.kjeldgaard@eb.dk
License: UNKNOWN
Platform: UNKNOWN
Classifier: Programming Language :: Python :: 3
Classifier: License :: OSI Approved :: MIT License
Requires-Python: >=3.6
Requires-Dist: torch
Requires-Dist: transformers
Requires-Dist: sklearn
Requires-Dist: nltk
Requires-Dist: pandas
Requires-Dist: progressbar
Requires-Dist: pyconll
